{
  "type": "patch",
  "comment": "* Completed removed Kendo SVG Icons and standardized on Font Awesome. Done for consistency, simplicity and also because Kendo SVG Icons seem to be having a major impact on rendering performance/resizing/etc * In several areas while removing KendoSVG and replacing with Font Awesome, implemented the new Angular 17 style control flow (@if instead of *ngIf as an example)",
  "packageName": "@memberjunction/ng-simple-record-list",
  "email": "97354817+AN-BC@users.noreply.github.com",
  "dependentChangeType": "patch"
}
