[
  {
    "fields": {
      "Name": "Personify360",
      "Description": "Personify360 integration connector for MemberJunction",
      "ClassName": "Personify360Connector",
      "ImportPath": "@memberjunction/integration-connectors",
      "NavigationBaseURL": null,
      "BatchMaxRequestCount": -1,
      "BatchRequestWaitTime": -1,
      "Icon": "fa-solid fa-building",
      "CredentialTypeID": "@lookup:MJ: Credential Types.Name=Personify360 OAuth"
    },
    "relatedEntities": {
      "MJ: Integration Objects": [
        {
          "fields": {
            "IntegrationID": "@parent:ID",
            "Name": "Organizations",
            "DisplayName": "Organization",
            "Description": "Member organizations (companies) in Personify360 Vault",
            "Category": "Core",
            "APIPath": "/Organizations",
            "ResponseDataKey": "data",
            "DefaultPageSize": 200,
            "SupportsPagination": true,
            "PaginationType": "PageNumber",
            "SupportsIncrementalSync": true,
            "SupportsWrite": true,
            "Sequence": 1,
            "Status": "Active"
          },
          "relatedEntities": {
            "MJ: Integration Object Fields": [
              {
                "fields": {
                  "IntegrationObjectID": "@parent:ID",
                  "Name": "id",
                  "DisplayName": "id",
                  "Type": "nvarchar",
                  "Length": 255,
                  "IsPrimaryKey": true,
                  "IsForeignKey": false,
                  "IsRequired": true,
                  "IsReadOnly": true,
                  "IsUniqueKey": true,
                  "AllowsNull": false,
                  "Sequence": 1,
                  "Status": "Active"
                }
              },
              {
                "fields": {
                  "IntegrationObjectID": "@parent:ID",
                  "Name": "createdOn",
                  "DisplayName": "createdOn",
                  "Type": "datetime",
                  "Length": null,
                  "IsPrimaryKey": false,
                  "IsForeignKey": false,
                  "IsRequired": false,
                  "IsReadOnly": true,
                  "IsUniqueKey": false,
                  "AllowsNull": true,
                  "Sequence": 2,
                  "Status": "Active"
                }
              },
              {
                "fields": {
                  "IntegrationObjectID": "@parent:ID",
                  "Name": "modifiedOn",
                  "DisplayName": "modifiedOn",
                  "Type": "datetime",
                  "Length": null,
                  "IsPrimaryKey": false,
                  "IsForeignKey": false,
                  "IsRequired": false,
                  "IsReadOnly": true,
                  "IsUniqueKey": false,
                  "AllowsNull": true,
                  "Sequence": 3,
                  "Status": "Active"
                }
              }
            ]
          }
        },
        {
          "fields": {
            "IntegrationID": "@parent:ID",
            "Name": "Individuals",
            "DisplayName": "Individual (Member)",
            "Description": "Individual member and contact records in Personify360 Vault",
            "Category": "Core",
            "APIPath": "/Individuals",
            "ResponseDataKey": "data",
            "DefaultPageSize": 200,
            "SupportsPagination": true,
            "PaginationType": "PageNumber",
            "SupportsIncrementalSync": true,
            "SupportsWrite": true,
            "Sequence": 2,
            "Status": "Active"
          },
          "relatedEntities": {
            "MJ: Integration Object Fields": [
              {
                "fields": {
                  "IntegrationObjectID": "@parent:ID",
                  "Name": "id",
                  "DisplayName": "id",
                  "Type": "nvarchar",
                  "Length": 255,
                  "IsPrimaryKey": true,
                  "IsForeignKey": false,
                  "IsRequired": true,
                  "IsReadOnly": true,
                  "IsUniqueKey": true,
                  "AllowsNull": false,
                  "Sequence": 1,
                  "Status": "Active"
                }
              },
              {
                "fields": {
                  "IntegrationObjectID": "@parent:ID",
                  "Name": "createdOn",
                  "DisplayName": "createdOn",
                  "Type": "datetime",
                  "Length": null,
                  "IsPrimaryKey": false,
                  "IsForeignKey": false,
                  "IsRequired": false,
                  "IsReadOnly": true,
                  "IsUniqueKey": false,
                  "AllowsNull": true,
                  "Sequence": 2,
                  "Status": "Active"
                }
              },
              {
                "fields": {
                  "IntegrationObjectID": "@parent:ID",
                  "Name": "modifiedOn",
                  "DisplayName": "modifiedOn",
                  "Type": "datetime",
                  "Length": null,
                  "IsPrimaryKey": false,
                  "IsForeignKey": false,
                  "IsRequired": false,
                  "IsReadOnly": true,
                  "IsUniqueKey": false,
                  "AllowsNull": true,
                  "Sequence": 3,
                  "Status": "Active"
                }
              }
            ]
          }
        },
        {
          "fields": {
            "IntegrationID": "@parent:ID",
            "Name": "Memberships",
            "DisplayName": "Membership",
            "Description": "Membership records linking individuals/organizations to membership types",
            "Category": "Core",
            "APIPath": "/Memberships",
            "ResponseDataKey": "data",
            "DefaultPageSize": 200,
            "SupportsPagination": true,
            "PaginationType": "PageNumber",
            "SupportsIncrementalSync": true,
            "SupportsWrite": true,
            "Sequence": 3,
            "Status": "Active"
          },
          "relatedEntities": {
            "MJ: Integration Object Fields": [
              {
                "fields": {
                  "IntegrationObjectID": "@parent:ID",
                  "Name": "id",
                  "DisplayName": "id",
                  "Type": "nvarchar",
                  "Length": 255,
                  "IsPrimaryKey": true,
                  "IsForeignKey": false,
                  "IsRequired": true,
                  "IsReadOnly": true,
                  "IsUniqueKey": true,
                  "AllowsNull": false,
                  "Sequence": 1,
                  "Status": "Active"
                }
              },
              {
                "fields": {
                  "IntegrationObjectID": "@parent:ID",
                  "Name": "beginDate",
                  "DisplayName": "beginDate",
                  "Type": "datetime",
                  "Length": null,
                  "IsPrimaryKey": false,
                  "IsForeignKey": false,
                  "IsRequired": false,
                  "IsReadOnly": true,
                  "IsUniqueKey": false,
                  "AllowsNull": true,
                  "Sequence": 2,
                  "Status": "Active"
                }
              },
              {
                "fields": {
                  "IntegrationObjectID": "@parent:ID",
                  "Name": "endDate",
                  "DisplayName": "endDate",
                  "Type": "datetime",
                  "Length": null,
                  "IsPrimaryKey": false,
                  "IsForeignKey": false,
                  "IsRequired": false,
                  "IsReadOnly": true,
                  "IsUniqueKey": false,
                  "AllowsNull": true,
                  "Sequence": 3,
                  "Status": "Active"
                }
              },
              {
                "fields": {
                  "IntegrationObjectID": "@parent:ID",
                  "Name": "paidThruDate",
                  "DisplayName": "paidThruDate",
                  "Type": "datetime",
                  "Length": null,
                  "IsPrimaryKey": false,
                  "IsForeignKey": false,
                  "IsRequired": false,
                  "IsReadOnly": true,
                  "IsUniqueKey": false,
                  "AllowsNull": true,
                  "Sequence": 4,
                  "Status": "Active"
                }
              }
            ]
          }
        },
        {
          "fields": {
            "IntegrationID": "@parent:ID",
            "Name": "Addresses",
            "DisplayName": "Address",
            "Description": "Addresses for individuals and organizations",
            "Category": "Core",
            "APIPath": "/Addresses",
            "ResponseDataKey": "data",
            "DefaultPageSize": 200,
            "SupportsPagination": true,
            "PaginationType": "PageNumber",
            "SupportsIncrementalSync": true,
            "SupportsWrite": true,
            "Sequence": 4,
            "Status": "Active"
          },
          "relatedEntities": {
            "MJ: Integration Object Fields": [
              {
                "fields": {
                  "IntegrationObjectID": "@parent:ID",
                  "Name": "id",
                  "DisplayName": "id",
                  "Type": "nvarchar",
                  "Length": 255,
                  "IsPrimaryKey": true,
                  "IsForeignKey": false,
                  "IsRequired": true,
                  "IsReadOnly": true,
                  "IsUniqueKey": true,
                  "AllowsNull": false,
                  "Sequence": 1,
                  "Status": "Active"
                }
              }
            ]
          }
        },
        {
          "fields": {
            "IntegrationID": "@parent:ID",
            "Name": "Events",
            "DisplayName": "Event",
            "Description": "Events in Personify360",
            "Category": "Core",
            "APIPath": "/Events",
            "ResponseDataKey": "data",
            "DefaultPageSize": 200,
            "SupportsPagination": true,
            "PaginationType": "PageNumber",
            "SupportsIncrementalSync": true,
            "SupportsWrite": true,
            "Sequence": 5,
            "Status": "Active"
          },
          "relatedEntities": {
            "MJ: Integration Object Fields": [
              {
                "fields": {
                  "IntegrationObjectID": "@parent:ID",
                  "Name": "id",
                  "DisplayName": "id",
                  "Type": "nvarchar",
                  "Length": 255,
                  "IsPrimaryKey": true,
                  "IsForeignKey": false,
                  "IsRequired": true,
                  "IsReadOnly": true,
                  "IsUniqueKey": true,
                  "AllowsNull": false,
                  "Sequence": 1,
                  "Status": "Active"
                }
              },
              {
                "fields": {
                  "IntegrationObjectID": "@parent:ID",
                  "Name": "startDate",
                  "DisplayName": "startDate",
                  "Type": "datetime",
                  "Length": null,
                  "IsPrimaryKey": false,
                  "IsForeignKey": false,
                  "IsRequired": false,
                  "IsReadOnly": true,
                  "IsUniqueKey": false,
                  "AllowsNull": true,
                  "Sequence": 2,
                  "Status": "Active"
                }
              },
              {
                "fields": {
                  "IntegrationObjectID": "@parent:ID",
                  "Name": "endDate",
                  "DisplayName": "endDate",
                  "Type": "datetime",
                  "Length": null,
                  "IsPrimaryKey": false,
                  "IsForeignKey": false,
                  "IsRequired": false,
                  "IsReadOnly": true,
                  "IsUniqueKey": false,
                  "AllowsNull": true,
                  "Sequence": 3,
                  "Status": "Active"
                }
              }
            ]
          }
        },
        {
          "fields": {
            "IntegrationID": "@parent:ID",
            "Name": "Orders",
            "DisplayName": "Order / Transaction",
            "Description": "Purchase orders and transactions in Personify360 Gateway",
            "Category": "Core",
            "APIPath": "/Orders",
            "ResponseDataKey": "data",
            "DefaultPageSize": 200,
            "SupportsPagination": true,
            "PaginationType": "PageNumber",
            "SupportsIncrementalSync": true,
            "SupportsWrite": false,
            "Sequence": 6,
            "Status": "Active"
          },
          "relatedEntities": {
            "MJ: Integration Object Fields": [
              {
                "fields": {
                  "IntegrationObjectID": "@parent:ID",
                  "Name": "id",
                  "DisplayName": "id",
                  "Type": "nvarchar",
                  "Length": 255,
                  "IsPrimaryKey": true,
                  "IsForeignKey": false,
                  "IsRequired": true,
                  "IsReadOnly": true,
                  "IsUniqueKey": true,
                  "AllowsNull": false,
                  "Sequence": 1,
                  "Status": "Active"
                }
              },
              {
                "fields": {
                  "IntegrationObjectID": "@parent:ID",
                  "Name": "orderDate",
                  "DisplayName": "orderDate",
                  "Type": "datetime",
                  "Length": null,
                  "IsPrimaryKey": false,
                  "IsForeignKey": false,
                  "IsRequired": false,
                  "IsReadOnly": true,
                  "IsUniqueKey": false,
                  "AllowsNull": true,
                  "Sequence": 2,
                  "Status": "Active"
                }
              },
              {
                "fields": {
                  "IntegrationObjectID": "@parent:ID",
                  "Name": "createdOn",
                  "DisplayName": "createdOn",
                  "Type": "datetime",
                  "Length": null,
                  "IsPrimaryKey": false,
                  "IsForeignKey": false,
                  "IsRequired": false,
                  "IsReadOnly": true,
                  "IsUniqueKey": false,
                  "AllowsNull": true,
                  "Sequence": 3,
                  "Status": "Active"
                }
              }
            ]
          }
        },
        {
          "fields": {
            "IntegrationID": "@parent:ID",
            "Name": "UserAccounts",
            "DisplayName": "User Account",
            "Description": "User login accounts (Provisioning service)",
            "Category": "Core",
            "APIPath": "/UserAccounts",
            "ResponseDataKey": "data",
            "DefaultPageSize": 200,
            "SupportsPagination": true,
            "PaginationType": "PageNumber",
            "SupportsIncrementalSync": true,
            "SupportsWrite": false,
            "Sequence": 7,
            "Status": "Active"
          },
          "relatedEntities": {
            "MJ: Integration Object Fields": [
              {
                "fields": {
                  "IntegrationObjectID": "@parent:ID",
                  "Name": "id",
                  "DisplayName": "id",
                  "Type": "nvarchar",
                  "Length": 255,
                  "IsPrimaryKey": true,
                  "IsForeignKey": false,
                  "IsRequired": true,
                  "IsReadOnly": true,
                  "IsUniqueKey": true,
                  "AllowsNull": false,
                  "Sequence": 1,
                  "Status": "Active"
                }
              },
              {
                "fields": {
                  "IntegrationObjectID": "@parent:ID",
                  "Name": "lastLoginOn",
                  "DisplayName": "lastLoginOn",
                  "Type": "datetime",
                  "Length": null,
                  "IsPrimaryKey": false,
                  "IsForeignKey": false,
                  "IsRequired": false,
                  "IsReadOnly": true,
                  "IsUniqueKey": false,
                  "AllowsNull": true,
                  "Sequence": 2,
                  "Status": "Active"
                }
              }
            ]
          }
        },
        {
          "fields": {
            "IntegrationID": "@parent:ID",
            "Name": "EventRegistrations",
            "DisplayName": "Event Registration",
            "Description": "Event registrations",
            "Category": "Core",
            "APIPath": "/EventRegistrations",
            "ResponseDataKey": "data",
            "DefaultPageSize": 200,
            "SupportsPagination": true,
            "PaginationType": "PageNumber",
            "SupportsIncrementalSync": true,
            "SupportsWrite": true,
            "Sequence": 8,
            "Status": "Active"
          },
          "relatedEntities": {
            "MJ: Integration Object Fields": [
              {
                "fields": {
                  "IntegrationObjectID": "@parent:ID",
                  "Name": "id",
                  "DisplayName": "id",
                  "Type": "nvarchar",
                  "Length": 255,
                  "IsPrimaryKey": true,
                  "IsForeignKey": false,
                  "IsRequired": true,
                  "IsReadOnly": true,
                  "IsUniqueKey": true,
                  "AllowsNull": false,
                  "Sequence": 1,
                  "Status": "Active"
                }
              },
              {
                "fields": {
                  "IntegrationObjectID": "@parent:ID",
                  "Name": "eventId",
                  "DisplayName": "eventId",
                  "Type": "nvarchar",
                  "Length": 255,
                  "IsPrimaryKey": false,
                  "IsForeignKey": true,
                  "IsRequired": false,
                  "IsReadOnly": false,
                  "IsUniqueKey": false,
                  "AllowsNull": true,
                  "Sequence": 2,
                  "Status": "Active"
                }
              },
              {
                "fields": {
                  "IntegrationObjectID": "@parent:ID",
                  "Name": "memberId",
                  "DisplayName": "memberId",
                  "Type": "nvarchar",
                  "Length": 255,
                  "IsPrimaryKey": false,
                  "IsForeignKey": true,
                  "IsRequired": false,
                  "IsReadOnly": false,
                  "IsUniqueKey": false,
                  "AllowsNull": true,
                  "Sequence": 3,
                  "Status": "Active"
                }
              },
              {
                "fields": {
                  "IntegrationObjectID": "@parent:ID",
                  "Name": "modifiedOn",
                  "DisplayName": "modifiedOn",
                  "Type": "datetime",
                  "Length": null,
                  "IsPrimaryKey": false,
                  "IsForeignKey": false,
                  "IsRequired": false,
                  "IsReadOnly": true,
                  "IsUniqueKey": false,
                  "AllowsNull": true,
                  "Sequence": 4,
                  "Status": "Active"
                }
              }
            ]
          }
        },
        {
          "fields": {
            "IntegrationID": "@parent:ID",
            "Name": "Sessions",
            "DisplayName": "Event Session",
            "Description": "Sessions within events",
            "Category": "Core",
            "APIPath": "/Sessions",
            "ResponseDataKey": "data",
            "DefaultPageSize": 200,
            "SupportsPagination": true,
            "PaginationType": "PageNumber",
            "SupportsIncrementalSync": true,
            "SupportsWrite": true,
            "Sequence": 9,
            "Status": "Active"
          },
          "relatedEntities": {
            "MJ: Integration Object Fields": [
              {
                "fields": {
                  "IntegrationObjectID": "@parent:ID",
                  "Name": "id",
                  "DisplayName": "id",
                  "Type": "nvarchar",
                  "Length": 255,
                  "IsPrimaryKey": true,
                  "IsForeignKey": false,
                  "IsRequired": true,
                  "IsReadOnly": true,
                  "IsUniqueKey": true,
                  "AllowsNull": false,
                  "Sequence": 1,
                  "Status": "Active"
                }
              },
              {
                "fields": {
                  "IntegrationObjectID": "@parent:ID",
                  "Name": "eventId",
                  "DisplayName": "eventId",
                  "Type": "nvarchar",
                  "Length": 255,
                  "IsPrimaryKey": false,
                  "IsForeignKey": true,
                  "IsRequired": false,
                  "IsReadOnly": false,
                  "IsUniqueKey": false,
                  "AllowsNull": true,
                  "Sequence": 2,
                  "Status": "Active"
                }
              }
            ]
          }
        },
        {
          "fields": {
            "IntegrationID": "@parent:ID",
            "Name": "Speakers",
            "DisplayName": "Speaker",
            "Description": "Event speakers",
            "Category": "Core",
            "APIPath": "/Speakers",
            "ResponseDataKey": "data",
            "DefaultPageSize": 200,
            "SupportsPagination": true,
            "PaginationType": "PageNumber",
            "SupportsIncrementalSync": true,
            "SupportsWrite": true,
            "Sequence": 10,
            "Status": "Active"
          },
          "relatedEntities": {
            "MJ: Integration Object Fields": [
              {
                "fields": {
                  "IntegrationObjectID": "@parent:ID",
                  "Name": "id",
                  "DisplayName": "id",
                  "Type": "nvarchar",
                  "Length": 255,
                  "IsPrimaryKey": true,
                  "IsForeignKey": false,
                  "IsRequired": true,
                  "IsReadOnly": true,
                  "IsUniqueKey": true,
                  "AllowsNull": false,
                  "Sequence": 1,
                  "Status": "Active"
                }
              }
            ]
          }
        },
        {
          "fields": {
            "IntegrationID": "@parent:ID",
            "Name": "Donations",
            "DisplayName": "Donation",
            "Description": "Donation/gift records",
            "Category": "Core",
            "APIPath": "/Donations",
            "ResponseDataKey": "data",
            "DefaultPageSize": 200,
            "SupportsPagination": true,
            "PaginationType": "PageNumber",
            "SupportsIncrementalSync": true,
            "SupportsWrite": true,
            "Sequence": 11,
            "Status": "Active"
          },
          "relatedEntities": {
            "MJ: Integration Object Fields": [
              {
                "fields": {
                  "IntegrationObjectID": "@parent:ID",
                  "Name": "id",
                  "DisplayName": "id",
                  "Type": "nvarchar",
                  "Length": 255,
                  "IsPrimaryKey": true,
                  "IsForeignKey": false,
                  "IsRequired": true,
                  "IsReadOnly": true,
                  "IsUniqueKey": true,
                  "AllowsNull": false,
                  "Sequence": 1,
                  "Status": "Active"
                }
              },
              {
                "fields": {
                  "IntegrationObjectID": "@parent:ID",
                  "Name": "memberId",
                  "DisplayName": "memberId",
                  "Type": "nvarchar",
                  "Length": 255,
                  "IsPrimaryKey": false,
                  "IsForeignKey": true,
                  "IsRequired": false,
                  "IsReadOnly": false,
                  "IsUniqueKey": false,
                  "AllowsNull": true,
                  "Sequence": 2,
                  "Status": "Active"
                }
              },
              {
                "fields": {
                  "IntegrationObjectID": "@parent:ID",
                  "Name": "modifiedOn",
                  "DisplayName": "modifiedOn",
                  "Type": "datetime",
                  "Length": null,
                  "IsPrimaryKey": false,
                  "IsForeignKey": false,
                  "IsRequired": false,
                  "IsReadOnly": true,
                  "IsUniqueKey": false,
                  "AllowsNull": true,
                  "Sequence": 3,
                  "Status": "Active"
                }
              }
            ]
          }
        },
        {
          "fields": {
            "IntegrationID": "@parent:ID",
            "Name": "P360Pledges",
            "DisplayName": "Pledge",
            "Description": "Pledge commitments",
            "Category": "Core",
            "APIPath": "/P360Pledges",
            "ResponseDataKey": "data",
            "DefaultPageSize": 200,
            "SupportsPagination": true,
            "PaginationType": "PageNumber",
            "SupportsIncrementalSync": true,
            "SupportsWrite": true,
            "Sequence": 12,
            "Status": "Active"
          },
          "relatedEntities": {
            "MJ: Integration Object Fields": [
              {
                "fields": {
                  "IntegrationObjectID": "@parent:ID",
                  "Name": "id",
                  "DisplayName": "id",
                  "Type": "nvarchar",
                  "Length": 255,
                  "IsPrimaryKey": true,
                  "IsForeignKey": false,
                  "IsRequired": true,
                  "IsReadOnly": true,
                  "IsUniqueKey": true,
                  "AllowsNull": false,
                  "Sequence": 1,
                  "Status": "Active"
                }
              },
              {
                "fields": {
                  "IntegrationObjectID": "@parent:ID",
                  "Name": "memberId",
                  "DisplayName": "memberId",
                  "Type": "nvarchar",
                  "Length": 255,
                  "IsPrimaryKey": false,
                  "IsForeignKey": true,
                  "IsRequired": false,
                  "IsReadOnly": false,
                  "IsUniqueKey": false,
                  "AllowsNull": true,
                  "Sequence": 2,
                  "Status": "Active"
                }
              }
            ]
          }
        },
        {
          "fields": {
            "IntegrationID": "@parent:ID",
            "Name": "P360Campaigns",
            "DisplayName": "Campaign",
            "Description": "Fundraising campaigns",
            "Category": "Core",
            "APIPath": "/P360Campaigns",
            "ResponseDataKey": "data",
            "DefaultPageSize": 200,
            "SupportsPagination": true,
            "PaginationType": "PageNumber",
            "SupportsIncrementalSync": true,
            "SupportsWrite": true,
            "Sequence": 13,
            "Status": "Active"
          },
          "relatedEntities": {
            "MJ: Integration Object Fields": [
              {
                "fields": {
                  "IntegrationObjectID": "@parent:ID",
                  "Name": "id",
                  "DisplayName": "id",
                  "Type": "nvarchar",
                  "Length": 255,
                  "IsPrimaryKey": true,
                  "IsForeignKey": false,
                  "IsRequired": true,
                  "IsReadOnly": true,
                  "IsUniqueKey": true,
                  "AllowsNull": false,
                  "Sequence": 1,
                  "Status": "Active"
                }
              }
            ]
          }
        },
        {
          "fields": {
            "IntegrationID": "@parent:ID",
            "Name": "P360Funds",
            "DisplayName": "Fund",
            "Description": "Fund/appeal codes",
            "Category": "Core",
            "APIPath": "/P360Funds",
            "ResponseDataKey": "data",
            "DefaultPageSize": 200,
            "SupportsPagination": true,
            "PaginationType": "PageNumber",
            "SupportsIncrementalSync": true,
            "SupportsWrite": true,
            "Sequence": 14,
            "Status": "Active"
          },
          "relatedEntities": {
            "MJ: Integration Object Fields": [
              {
                "fields": {
                  "IntegrationObjectID": "@parent:ID",
                  "Name": "id",
                  "DisplayName": "id",
                  "Type": "nvarchar",
                  "Length": 255,
                  "IsPrimaryKey": true,
                  "IsForeignKey": false,
                  "IsRequired": true,
                  "IsReadOnly": true,
                  "IsUniqueKey": true,
                  "AllowsNull": false,
                  "Sequence": 1,
                  "Status": "Active"
                }
              }
            ]
          }
        },
        {
          "fields": {
            "IntegrationID": "@parent:ID",
            "Name": "Committees",
            "DisplayName": "Committee",
            "Description": "Committees and boards",
            "Category": "Core",
            "APIPath": "/Committees",
            "ResponseDataKey": "data",
            "DefaultPageSize": 200,
            "SupportsPagination": true,
            "PaginationType": "PageNumber",
            "SupportsIncrementalSync": true,
            "SupportsWrite": true,
            "Sequence": 15,
            "Status": "Active"
          },
          "relatedEntities": {
            "MJ: Integration Object Fields": [
              {
                "fields": {
                  "IntegrationObjectID": "@parent:ID",
                  "Name": "id",
                  "DisplayName": "id",
                  "Type": "nvarchar",
                  "Length": 255,
                  "IsPrimaryKey": true,
                  "IsForeignKey": false,
                  "IsRequired": true,
                  "IsReadOnly": true,
                  "IsUniqueKey": true,
                  "AllowsNull": false,
                  "Sequence": 1,
                  "Status": "Active"
                }
              }
            ]
          }
        },
        {
          "fields": {
            "IntegrationID": "@parent:ID",
            "Name": "CommitteeMembers",
            "DisplayName": "Committee Member",
            "Description": "Committee membership",
            "Category": "Core",
            "APIPath": "/CommitteeMembers",
            "ResponseDataKey": "data",
            "DefaultPageSize": 200,
            "SupportsPagination": true,
            "PaginationType": "PageNumber",
            "SupportsIncrementalSync": true,
            "SupportsWrite": true,
            "Sequence": 16,
            "Status": "Active"
          },
          "relatedEntities": {
            "MJ: Integration Object Fields": [
              {
                "fields": {
                  "IntegrationObjectID": "@parent:ID",
                  "Name": "id",
                  "DisplayName": "id",
                  "Type": "nvarchar",
                  "Length": 255,
                  "IsPrimaryKey": true,
                  "IsForeignKey": false,
                  "IsRequired": true,
                  "IsReadOnly": true,
                  "IsUniqueKey": true,
                  "AllowsNull": false,
                  "Sequence": 1,
                  "Status": "Active"
                }
              },
              {
                "fields": {
                  "IntegrationObjectID": "@parent:ID",
                  "Name": "committeeId",
                  "DisplayName": "committeeId",
                  "Type": "nvarchar",
                  "Length": 255,
                  "IsPrimaryKey": false,
                  "IsForeignKey": true,
                  "IsRequired": false,
                  "IsReadOnly": false,
                  "IsUniqueKey": false,
                  "AllowsNull": true,
                  "Sequence": 2,
                  "Status": "Active"
                }
              },
              {
                "fields": {
                  "IntegrationObjectID": "@parent:ID",
                  "Name": "memberId",
                  "DisplayName": "memberId",
                  "Type": "nvarchar",
                  "Length": 255,
                  "IsPrimaryKey": false,
                  "IsForeignKey": true,
                  "IsRequired": false,
                  "IsReadOnly": false,
                  "IsUniqueKey": false,
                  "AllowsNull": true,
                  "Sequence": 3,
                  "Status": "Active"
                }
              }
            ]
          }
        },
        {
          "fields": {
            "IntegrationID": "@parent:ID",
            "Name": "Certifications",
            "DisplayName": "Certification",
            "Description": "Certification records",
            "Category": "Core",
            "APIPath": "/Certifications",
            "ResponseDataKey": "data",
            "DefaultPageSize": 200,
            "SupportsPagination": true,
            "PaginationType": "PageNumber",
            "SupportsIncrementalSync": true,
            "SupportsWrite": true,
            "Sequence": 17,
            "Status": "Active"
          },
          "relatedEntities": {
            "MJ: Integration Object Fields": [
              {
                "fields": {
                  "IntegrationObjectID": "@parent:ID",
                  "Name": "id",
                  "DisplayName": "id",
                  "Type": "nvarchar",
                  "Length": 255,
                  "IsPrimaryKey": true,
                  "IsForeignKey": false,
                  "IsRequired": true,
                  "IsReadOnly": true,
                  "IsUniqueKey": true,
                  "AllowsNull": false,
                  "Sequence": 1,
                  "Status": "Active"
                }
              },
              {
                "fields": {
                  "IntegrationObjectID": "@parent:ID",
                  "Name": "memberId",
                  "DisplayName": "memberId",
                  "Type": "nvarchar",
                  "Length": 255,
                  "IsPrimaryKey": false,
                  "IsForeignKey": true,
                  "IsRequired": false,
                  "IsReadOnly": false,
                  "IsUniqueKey": false,
                  "AllowsNull": true,
                  "Sequence": 2,
                  "Status": "Active"
                }
              }
            ]
          }
        },
        {
          "fields": {
            "IntegrationID": "@parent:ID",
            "Name": "ContinuingEducation",
            "DisplayName": "CE Credit",
            "Description": "Continuing education credits",
            "Category": "Core",
            "APIPath": "/ContinuingEducation",
            "ResponseDataKey": "data",
            "DefaultPageSize": 200,
            "SupportsPagination": true,
            "PaginationType": "PageNumber",
            "SupportsIncrementalSync": true,
            "SupportsWrite": true,
            "Sequence": 18,
            "Status": "Active"
          },
          "relatedEntities": {
            "MJ: Integration Object Fields": [
              {
                "fields": {
                  "IntegrationObjectID": "@parent:ID",
                  "Name": "id",
                  "DisplayName": "id",
                  "Type": "nvarchar",
                  "Length": 255,
                  "IsPrimaryKey": true,
                  "IsForeignKey": false,
                  "IsRequired": true,
                  "IsReadOnly": true,
                  "IsUniqueKey": true,
                  "AllowsNull": false,
                  "Sequence": 1,
                  "Status": "Active"
                }
              },
              {
                "fields": {
                  "IntegrationObjectID": "@parent:ID",
                  "Name": "memberId",
                  "DisplayName": "memberId",
                  "Type": "nvarchar",
                  "Length": 255,
                  "IsPrimaryKey": false,
                  "IsForeignKey": true,
                  "IsRequired": false,
                  "IsReadOnly": false,
                  "IsUniqueKey": false,
                  "AllowsNull": true,
                  "Sequence": 2,
                  "Status": "Active"
                }
              }
            ]
          }
        },
        {
          "fields": {
            "IntegrationID": "@parent:ID",
            "Name": "P360Products",
            "DisplayName": "Product",
            "Description": "Product catalog",
            "Category": "Core",
            "APIPath": "/P360Products",
            "ResponseDataKey": "data",
            "DefaultPageSize": 200,
            "SupportsPagination": true,
            "PaginationType": "PageNumber",
            "SupportsIncrementalSync": true,
            "SupportsWrite": true,
            "Sequence": 19,
            "Status": "Active"
          },
          "relatedEntities": {
            "MJ: Integration Object Fields": [
              {
                "fields": {
                  "IntegrationObjectID": "@parent:ID",
                  "Name": "id",
                  "DisplayName": "id",
                  "Type": "nvarchar",
                  "Length": 255,
                  "IsPrimaryKey": true,
                  "IsForeignKey": false,
                  "IsRequired": true,
                  "IsReadOnly": true,
                  "IsUniqueKey": true,
                  "AllowsNull": false,
                  "Sequence": 1,
                  "Status": "Active"
                }
              }
            ]
          }
        },
        {
          "fields": {
            "IntegrationID": "@parent:ID",
            "Name": "P360Payments",
            "DisplayName": "Payment",
            "Description": "Payment transactions",
            "Category": "Core",
            "APIPath": "/P360Payments",
            "ResponseDataKey": "data",
            "DefaultPageSize": 200,
            "SupportsPagination": true,
            "PaginationType": "PageNumber",
            "SupportsIncrementalSync": true,
            "SupportsWrite": false,
            "Sequence": 20,
            "Status": "Active"
          },
          "relatedEntities": {
            "MJ: Integration Object Fields": [
              {
                "fields": {
                  "IntegrationObjectID": "@parent:ID",
                  "Name": "id",
                  "DisplayName": "id",
                  "Type": "nvarchar",
                  "Length": 255,
                  "IsPrimaryKey": true,
                  "IsForeignKey": false,
                  "IsRequired": true,
                  "IsReadOnly": true,
                  "IsUniqueKey": true,
                  "AllowsNull": false,
                  "Sequence": 1,
                  "Status": "Active"
                }
              },
              {
                "fields": {
                  "IntegrationObjectID": "@parent:ID",
                  "Name": "modifiedOn",
                  "DisplayName": "modifiedOn",
                  "Type": "datetime",
                  "Length": null,
                  "IsPrimaryKey": false,
                  "IsForeignKey": false,
                  "IsRequired": false,
                  "IsReadOnly": true,
                  "IsUniqueKey": false,
                  "AllowsNull": true,
                  "Sequence": 2,
                  "Status": "Active"
                }
              }
            ]
          }
        },
        {
          "fields": {
            "IntegrationID": "@parent:ID",
            "Name": "P360Invoices",
            "DisplayName": "Invoice",
            "Description": "Invoice records",
            "Category": "Core",
            "APIPath": "/P360Invoices",
            "ResponseDataKey": "data",
            "DefaultPageSize": 200,
            "SupportsPagination": true,
            "PaginationType": "PageNumber",
            "SupportsIncrementalSync": true,
            "SupportsWrite": false,
            "Sequence": 21,
            "Status": "Active"
          },
          "relatedEntities": {
            "MJ: Integration Object Fields": [
              {
                "fields": {
                  "IntegrationObjectID": "@parent:ID",
                  "Name": "id",
                  "DisplayName": "id",
                  "Type": "nvarchar",
                  "Length": 255,
                  "IsPrimaryKey": true,
                  "IsForeignKey": false,
                  "IsRequired": true,
                  "IsReadOnly": true,
                  "IsUniqueKey": true,
                  "AllowsNull": false,
                  "Sequence": 1,
                  "Status": "Active"
                }
              }
            ]
          }
        },
        {
          "fields": {
            "IntegrationID": "@parent:ID",
            "Name": "Communications",
            "DisplayName": "Communication",
            "Description": "Email/phone/fax records",
            "Category": "Core",
            "APIPath": "/Communications",
            "ResponseDataKey": "data",
            "DefaultPageSize": 200,
            "SupportsPagination": true,
            "PaginationType": "PageNumber",
            "SupportsIncrementalSync": true,
            "SupportsWrite": true,
            "Sequence": 22,
            "Status": "Active"
          },
          "relatedEntities": {
            "MJ: Integration Object Fields": [
              {
                "fields": {
                  "IntegrationObjectID": "@parent:ID",
                  "Name": "id",
                  "DisplayName": "id",
                  "Type": "nvarchar",
                  "Length": 255,
                  "IsPrimaryKey": true,
                  "IsForeignKey": false,
                  "IsRequired": true,
                  "IsReadOnly": true,
                  "IsUniqueKey": true,
                  "AllowsNull": false,
                  "Sequence": 1,
                  "Status": "Active"
                }
              },
              {
                "fields": {
                  "IntegrationObjectID": "@parent:ID",
                  "Name": "memberId",
                  "DisplayName": "memberId",
                  "Type": "nvarchar",
                  "Length": 255,
                  "IsPrimaryKey": false,
                  "IsForeignKey": true,
                  "IsRequired": false,
                  "IsReadOnly": false,
                  "IsUniqueKey": false,
                  "AllowsNull": true,
                  "Sequence": 2,
                  "Status": "Active"
                }
              }
            ]
          }
        },
        {
          "fields": {
            "IntegrationID": "@parent:ID",
            "Name": "Relationships",
            "DisplayName": "Relationship",
            "Description": "Constituent relationships",
            "Category": "Core",
            "APIPath": "/Relationships",
            "ResponseDataKey": "data",
            "DefaultPageSize": 200,
            "SupportsPagination": true,
            "PaginationType": "PageNumber",
            "SupportsIncrementalSync": true,
            "SupportsWrite": true,
            "Sequence": 23,
            "Status": "Active"
          },
          "relatedEntities": {
            "MJ: Integration Object Fields": [
              {
                "fields": {
                  "IntegrationObjectID": "@parent:ID",
                  "Name": "id",
                  "DisplayName": "id",
                  "Type": "nvarchar",
                  "Length": 255,
                  "IsPrimaryKey": true,
                  "IsForeignKey": false,
                  "IsRequired": true,
                  "IsReadOnly": true,
                  "IsUniqueKey": true,
                  "AllowsNull": false,
                  "Sequence": 1,
                  "Status": "Active"
                }
              }
            ]
          }
        },
        {
          "fields": {
            "IntegrationID": "@parent:ID",
            "Name": "MembershipCategories",
            "DisplayName": "Membership Category",
            "Description": "Membership type definitions",
            "Category": "Core",
            "APIPath": "/MembershipCategories",
            "ResponseDataKey": "data",
            "DefaultPageSize": 200,
            "SupportsPagination": true,
            "PaginationType": "PageNumber",
            "SupportsIncrementalSync": true,
            "SupportsWrite": false,
            "Sequence": 24,
            "Status": "Active"
          },
          "relatedEntities": {
            "MJ: Integration Object Fields": [
              {
                "fields": {
                  "IntegrationObjectID": "@parent:ID",
                  "Name": "id",
                  "DisplayName": "id",
                  "Type": "nvarchar",
                  "Length": 255,
                  "IsPrimaryKey": true,
                  "IsForeignKey": false,
                  "IsRequired": true,
                  "IsReadOnly": true,
                  "IsUniqueKey": true,
                  "AllowsNull": false,
                  "Sequence": 1,
                  "Status": "Active"
                }
              }
            ]
          }
        },
        {
          "fields": {
            "IntegrationID": "@parent:ID",
            "Name": "SessionRegistrations",
            "DisplayName": "Session Registration",
            "Description": "Session-level registrations",
            "Category": "Core",
            "APIPath": "/SessionRegistrations",
            "ResponseDataKey": "data",
            "DefaultPageSize": 200,
            "SupportsPagination": true,
            "PaginationType": "PageNumber",
            "SupportsIncrementalSync": true,
            "SupportsWrite": true,
            "Sequence": 25,
            "Status": "Active"
          },
          "relatedEntities": {
            "MJ: Integration Object Fields": [
              {
                "fields": {
                  "IntegrationObjectID": "@parent:ID",
                  "Name": "id",
                  "DisplayName": "id",
                  "Type": "nvarchar",
                  "Length": 255,
                  "IsPrimaryKey": true,
                  "IsForeignKey": false,
                  "IsRequired": true,
                  "IsReadOnly": true,
                  "IsUniqueKey": true,
                  "AllowsNull": false,
                  "Sequence": 1,
                  "Status": "Active"
                }
              },
              {
                "fields": {
                  "IntegrationObjectID": "@parent:ID",
                  "Name": "sessionId",
                  "DisplayName": "sessionId",
                  "Type": "nvarchar",
                  "Length": 255,
                  "IsPrimaryKey": false,
                  "IsForeignKey": true,
                  "IsRequired": false,
                  "IsReadOnly": false,
                  "IsUniqueKey": false,
                  "AllowsNull": true,
                  "Sequence": 2,
                  "Status": "Active"
                }
              },
              {
                "fields": {
                  "IntegrationObjectID": "@parent:ID",
                  "Name": "memberId",
                  "DisplayName": "memberId",
                  "Type": "nvarchar",
                  "Length": 255,
                  "IsPrimaryKey": false,
                  "IsForeignKey": true,
                  "IsRequired": false,
                  "IsReadOnly": false,
                  "IsUniqueKey": false,
                  "AllowsNull": true,
                  "Sequence": 3,
                  "Status": "Active"
                }
              }
            ]
          }
        },
        {
          "fields": {
            "IntegrationID": "@parent:ID",
            "Name": "Exhibitors",
            "DisplayName": "Exhibitor",
            "Description": "Event exhibitors",
            "Category": "Core",
            "APIPath": "/Exhibitors",
            "ResponseDataKey": "data",
            "DefaultPageSize": 200,
            "SupportsPagination": true,
            "PaginationType": "PageNumber",
            "SupportsIncrementalSync": true,
            "SupportsWrite": true,
            "Sequence": 26,
            "Status": "Active"
          },
          "relatedEntities": {
            "MJ: Integration Object Fields": [
              {
                "fields": {
                  "IntegrationObjectID": "@parent:ID",
                  "Name": "id",
                  "DisplayName": "id",
                  "Type": "nvarchar",
                  "Length": 255,
                  "IsPrimaryKey": true,
                  "IsForeignKey": false,
                  "IsRequired": true,
                  "IsReadOnly": true,
                  "IsUniqueKey": true,
                  "AllowsNull": false,
                  "Sequence": 1,
                  "Status": "Active"
                }
              },
              {
                "fields": {
                  "IntegrationObjectID": "@parent:ID",
                  "Name": "eventId",
                  "DisplayName": "eventId",
                  "Type": "nvarchar",
                  "Length": 255,
                  "IsPrimaryKey": false,
                  "IsForeignKey": true,
                  "IsRequired": false,
                  "IsReadOnly": false,
                  "IsUniqueKey": false,
                  "AllowsNull": true,
                  "Sequence": 2,
                  "Status": "Active"
                }
              }
            ]
          }
        },
        {
          "fields": {
            "IntegrationID": "@parent:ID",
            "Name": "Venues",
            "DisplayName": "Venue",
            "Description": "Event venues",
            "Category": "Core",
            "APIPath": "/Venues",
            "ResponseDataKey": "data",
            "DefaultPageSize": 200,
            "SupportsPagination": true,
            "PaginationType": "PageNumber",
            "SupportsIncrementalSync": true,
            "SupportsWrite": true,
            "Sequence": 27,
            "Status": "Active"
          },
          "relatedEntities": {
            "MJ: Integration Object Fields": [
              {
                "fields": {
                  "IntegrationObjectID": "@parent:ID",
                  "Name": "id",
                  "DisplayName": "id",
                  "Type": "nvarchar",
                  "Length": 255,
                  "IsPrimaryKey": true,
                  "IsForeignKey": false,
                  "IsRequired": true,
                  "IsReadOnly": true,
                  "IsUniqueKey": true,
                  "AllowsNull": false,
                  "Sequence": 1,
                  "Status": "Active"
                }
              }
            ]
          }
        },
        {
          "fields": {
            "IntegrationID": "@parent:ID",
            "Name": "GiftHistory",
            "DisplayName": "Gift History",
            "Description": "Historical giving summary view",
            "Category": "Core",
            "APIPath": "/GiftHistory",
            "ResponseDataKey": "data",
            "DefaultPageSize": 200,
            "SupportsPagination": true,
            "PaginationType": "PageNumber",
            "SupportsIncrementalSync": true,
            "SupportsWrite": false,
            "Sequence": 28,
            "Status": "Active"
          },
          "relatedEntities": {
            "MJ: Integration Object Fields": [
              {
                "fields": {
                  "IntegrationObjectID": "@parent:ID",
                  "Name": "memberId",
                  "DisplayName": "memberId",
                  "Type": "nvarchar",
                  "Length": 255,
                  "IsPrimaryKey": true,
                  "IsForeignKey": true,
                  "IsRequired": true,
                  "IsReadOnly": true,
                  "IsUniqueKey": true,
                  "AllowsNull": false,
                  "Sequence": 1,
                  "Status": "Active"
                }
              }
            ]
          }
        },
        {
          "fields": {
            "IntegrationID": "@parent:ID",
            "Name": "Receipts",
            "DisplayName": "Receipt",
            "Description": "Donation receipts",
            "Category": "Core",
            "APIPath": "/Receipts",
            "ResponseDataKey": "data",
            "DefaultPageSize": 200,
            "SupportsPagination": true,
            "PaginationType": "PageNumber",
            "SupportsIncrementalSync": true,
            "SupportsWrite": true,
            "Sequence": 29,
            "Status": "Active"
          },
          "relatedEntities": {
            "MJ: Integration Object Fields": [
              {
                "fields": {
                  "IntegrationObjectID": "@parent:ID",
                  "Name": "id",
                  "DisplayName": "id",
                  "Type": "nvarchar",
                  "Length": 255,
                  "IsPrimaryKey": true,
                  "IsForeignKey": false,
                  "IsRequired": true,
                  "IsReadOnly": true,
                  "IsUniqueKey": true,
                  "AllowsNull": false,
                  "Sequence": 1,
                  "Status": "Active"
                }
              },
              {
                "fields": {
                  "IntegrationObjectID": "@parent:ID",
                  "Name": "modifiedOn",
                  "DisplayName": "modifiedOn",
                  "Type": "datetime",
                  "Length": null,
                  "IsPrimaryKey": false,
                  "IsForeignKey": false,
                  "IsRequired": false,
                  "IsReadOnly": true,
                  "IsUniqueKey": false,
                  "AllowsNull": true,
                  "Sequence": 2,
                  "Status": "Active"
                }
              }
            ]
          }
        },
        {
          "fields": {
            "IntegrationID": "@parent:ID",
            "Name": "P360Education",
            "DisplayName": "Education",
            "Description": "Education/degree records",
            "Category": "Core",
            "APIPath": "/P360Education",
            "ResponseDataKey": "data",
            "DefaultPageSize": 200,
            "SupportsPagination": true,
            "PaginationType": "PageNumber",
            "SupportsIncrementalSync": true,
            "SupportsWrite": true,
            "Sequence": 30,
            "Status": "Active"
          },
          "relatedEntities": {
            "MJ: Integration Object Fields": [
              {
                "fields": {
                  "IntegrationObjectID": "@parent:ID",
                  "Name": "id",
                  "DisplayName": "id",
                  "Type": "nvarchar",
                  "Length": 255,
                  "IsPrimaryKey": true,
                  "IsForeignKey": false,
                  "IsRequired": true,
                  "IsReadOnly": true,
                  "IsUniqueKey": true,
                  "AllowsNull": false,
                  "Sequence": 1,
                  "Status": "Active"
                }
              },
              {
                "fields": {
                  "IntegrationObjectID": "@parent:ID",
                  "Name": "memberId",
                  "DisplayName": "memberId",
                  "Type": "nvarchar",
                  "Length": 255,
                  "IsPrimaryKey": false,
                  "IsForeignKey": true,
                  "IsRequired": false,
                  "IsReadOnly": false,
                  "IsUniqueKey": false,
                  "AllowsNull": true,
                  "Sequence": 2,
                  "Status": "Active"
                }
              }
            ]
          }
        },
        {
          "fields": {
            "IntegrationID": "@parent:ID",
            "Name": "Exams",
            "DisplayName": "Exam",
            "Description": "Exam records for certifications",
            "Category": "Core",
            "APIPath": "/Exams",
            "ResponseDataKey": "data",
            "DefaultPageSize": 200,
            "SupportsPagination": true,
            "PaginationType": "PageNumber",
            "SupportsIncrementalSync": true,
            "SupportsWrite": true,
            "Sequence": 31,
            "Status": "Active"
          },
          "relatedEntities": {
            "MJ: Integration Object Fields": [
              {
                "fields": {
                  "IntegrationObjectID": "@parent:ID",
                  "Name": "id",
                  "DisplayName": "id",
                  "Type": "nvarchar",
                  "Length": 255,
                  "IsPrimaryKey": true,
                  "IsForeignKey": false,
                  "IsRequired": true,
                  "IsReadOnly": true,
                  "IsUniqueKey": true,
                  "AllowsNull": false,
                  "Sequence": 1,
                  "Status": "Active"
                }
              },
              {
                "fields": {
                  "IntegrationObjectID": "@parent:ID",
                  "Name": "memberId",
                  "DisplayName": "memberId",
                  "Type": "nvarchar",
                  "Length": 255,
                  "IsPrimaryKey": false,
                  "IsForeignKey": true,
                  "IsRequired": false,
                  "IsReadOnly": false,
                  "IsUniqueKey": false,
                  "AllowsNull": true,
                  "Sequence": 2,
                  "Status": "Active"
                }
              }
            ]
          }
        },
        {
          "fields": {
            "IntegrationID": "@parent:ID",
            "Name": "OrderDetails",
            "DisplayName": "Order Detail",
            "Description": "Order line items",
            "Category": "Core",
            "APIPath": "/OrderDetails",
            "ResponseDataKey": "data",
            "DefaultPageSize": 200,
            "SupportsPagination": true,
            "PaginationType": "PageNumber",
            "SupportsIncrementalSync": true,
            "SupportsWrite": false,
            "Sequence": 32,
            "Status": "Active"
          },
          "relatedEntities": {
            "MJ: Integration Object Fields": [
              {
                "fields": {
                  "IntegrationObjectID": "@parent:ID",
                  "Name": "id",
                  "DisplayName": "id",
                  "Type": "nvarchar",
                  "Length": 255,
                  "IsPrimaryKey": true,
                  "IsForeignKey": false,
                  "IsRequired": true,
                  "IsReadOnly": true,
                  "IsUniqueKey": true,
                  "AllowsNull": false,
                  "Sequence": 1,
                  "Status": "Active"
                }
              },
              {
                "fields": {
                  "IntegrationObjectID": "@parent:ID",
                  "Name": "orderId",
                  "DisplayName": "orderId",
                  "Type": "nvarchar",
                  "Length": 255,
                  "IsPrimaryKey": false,
                  "IsForeignKey": true,
                  "IsRequired": false,
                  "IsReadOnly": false,
                  "IsUniqueKey": false,
                  "AllowsNull": true,
                  "Sequence": 2,
                  "Status": "Active"
                }
              }
            ]
          }
        },
        {
          "fields": {
            "IntegrationID": "@parent:ID",
            "Name": "ShoppingCarts",
            "DisplayName": "Shopping Cart",
            "Description": "Active shopping cart records",
            "Category": "Core",
            "APIPath": "/ShoppingCarts",
            "ResponseDataKey": "data",
            "DefaultPageSize": 200,
            "SupportsPagination": true,
            "PaginationType": "PageNumber",
            "SupportsIncrementalSync": true,
            "SupportsWrite": true,
            "Sequence": 33,
            "Status": "Active"
          },
          "relatedEntities": {
            "MJ: Integration Object Fields": [
              {
                "fields": {
                  "IntegrationObjectID": "@parent:ID",
                  "Name": "id",
                  "DisplayName": "id",
                  "Type": "nvarchar",
                  "Length": 255,
                  "IsPrimaryKey": true,
                  "IsForeignKey": false,
                  "IsRequired": true,
                  "IsReadOnly": true,
                  "IsUniqueKey": true,
                  "AllowsNull": false,
                  "Sequence": 1,
                  "Status": "Active"
                }
              },
              {
                "fields": {
                  "IntegrationObjectID": "@parent:ID",
                  "Name": "memberId",
                  "DisplayName": "memberId",
                  "Type": "nvarchar",
                  "Length": 255,
                  "IsPrimaryKey": false,
                  "IsForeignKey": true,
                  "IsRequired": false,
                  "IsReadOnly": false,
                  "IsUniqueKey": false,
                  "AllowsNull": true,
                  "Sequence": 2,
                  "Status": "Active"
                }
              }
            ]
          }
        },
        {
          "fields": {
            "IntegrationID": "@parent:ID",
            "Name": "Dues",
            "DisplayName": "Dues",
            "Description": "Dues billing records",
            "Category": "Core",
            "APIPath": "/Dues",
            "ResponseDataKey": "data",
            "DefaultPageSize": 200,
            "SupportsPagination": true,
            "PaginationType": "PageNumber",
            "SupportsIncrementalSync": true,
            "SupportsWrite": true,
            "Sequence": 34,
            "Status": "Active"
          },
          "relatedEntities": {
            "MJ: Integration Object Fields": [
              {
                "fields": {
                  "IntegrationObjectID": "@parent:ID",
                  "Name": "id",
                  "DisplayName": "id",
                  "Type": "nvarchar",
                  "Length": 255,
                  "IsPrimaryKey": true,
                  "IsForeignKey": false,
                  "IsRequired": true,
                  "IsReadOnly": true,
                  "IsUniqueKey": true,
                  "AllowsNull": false,
                  "Sequence": 1,
                  "Status": "Active"
                }
              },
              {
                "fields": {
                  "IntegrationObjectID": "@parent:ID",
                  "Name": "memberId",
                  "DisplayName": "memberId",
                  "Type": "nvarchar",
                  "Length": 255,
                  "IsPrimaryKey": false,
                  "IsForeignKey": true,
                  "IsRequired": false,
                  "IsReadOnly": false,
                  "IsUniqueKey": false,
                  "AllowsNull": true,
                  "Sequence": 2,
                  "Status": "Active"
                }
              },
              {
                "fields": {
                  "IntegrationObjectID": "@parent:ID",
                  "Name": "modifiedOn",
                  "DisplayName": "modifiedOn",
                  "Type": "datetime",
                  "Length": null,
                  "IsPrimaryKey": false,
                  "IsForeignKey": false,
                  "IsRequired": false,
                  "IsReadOnly": true,
                  "IsUniqueKey": false,
                  "AllowsNull": true,
                  "Sequence": 3,
                  "Status": "Active"
                }
              }
            ]
          }
        },
        {
          "fields": {
            "IntegrationID": "@parent:ID",
            "Name": "Subscriptions",
            "DisplayName": "Subscription",
            "Description": "Publication subscriptions",
            "Category": "Core",
            "APIPath": "/Subscriptions",
            "ResponseDataKey": "data",
            "DefaultPageSize": 200,
            "SupportsPagination": true,
            "PaginationType": "PageNumber",
            "SupportsIncrementalSync": true,
            "SupportsWrite": true,
            "Sequence": 35,
            "Status": "Active"
          },
          "relatedEntities": {
            "MJ: Integration Object Fields": [
              {
                "fields": {
                  "IntegrationObjectID": "@parent:ID",
                  "Name": "id",
                  "DisplayName": "id",
                  "Type": "nvarchar",
                  "Length": 255,
                  "IsPrimaryKey": true,
                  "IsForeignKey": false,
                  "IsRequired": true,
                  "IsReadOnly": true,
                  "IsUniqueKey": true,
                  "AllowsNull": false,
                  "Sequence": 1,
                  "Status": "Active"
                }
              },
              {
                "fields": {
                  "IntegrationObjectID": "@parent:ID",
                  "Name": "memberId",
                  "DisplayName": "memberId",
                  "Type": "nvarchar",
                  "Length": 255,
                  "IsPrimaryKey": false,
                  "IsForeignKey": true,
                  "IsRequired": false,
                  "IsReadOnly": false,
                  "IsUniqueKey": false,
                  "AllowsNull": true,
                  "Sequence": 2,
                  "Status": "Active"
                }
              }
            ]
          }
        },
        {
          "fields": {
            "IntegrationID": "@parent:ID",
            "Name": "P360MembershipTypes",
            "DisplayName": "Membership Type",
            "Description": "Membership subtype definitions",
            "Category": "Core",
            "APIPath": "/P360MembershipTypes",
            "ResponseDataKey": "data",
            "DefaultPageSize": 200,
            "SupportsPagination": true,
            "PaginationType": "PageNumber",
            "SupportsIncrementalSync": true,
            "SupportsWrite": false,
            "Sequence": 36,
            "Status": "Active"
          },
          "relatedEntities": {
            "MJ: Integration Object Fields": [
              {
                "fields": {
                  "IntegrationObjectID": "@parent:ID",
                  "Name": "id",
                  "DisplayName": "id",
                  "Type": "nvarchar",
                  "Length": 255,
                  "IsPrimaryKey": true,
                  "IsForeignKey": false,
                  "IsRequired": true,
                  "IsReadOnly": true,
                  "IsUniqueKey": true,
                  "AllowsNull": false,
                  "Sequence": 1,
                  "Status": "Active"
                }
              }
            ]
          }
        },
        {
          "fields": {
            "IntegrationID": "@parent:ID",
            "Name": "Demographics",
            "DisplayName": "Demographics",
            "Description": "Demographic data",
            "Category": "Core",
            "APIPath": "/Demographics",
            "ResponseDataKey": "data",
            "DefaultPageSize": 200,
            "SupportsPagination": true,
            "PaginationType": "PageNumber",
            "SupportsIncrementalSync": true,
            "SupportsWrite": true,
            "Sequence": 37,
            "Status": "Active"
          },
          "relatedEntities": {
            "MJ: Integration Object Fields": [
              {
                "fields": {
                  "IntegrationObjectID": "@parent:ID",
                  "Name": "memberId",
                  "DisplayName": "memberId",
                  "Type": "nvarchar",
                  "Length": 255,
                  "IsPrimaryKey": true,
                  "IsForeignKey": true,
                  "IsRequired": true,
                  "IsReadOnly": true,
                  "IsUniqueKey": true,
                  "AllowsNull": false,
                  "Sequence": 1,
                  "Status": "Active"
                }
              }
            ]
          }
        },
        {
          "fields": {
            "IntegrationID": "@parent:ID",
            "Name": "Preferences",
            "DisplayName": "Preference",
            "Description": "Communication preferences",
            "Category": "Core",
            "APIPath": "/Preferences",
            "ResponseDataKey": "data",
            "DefaultPageSize": 200,
            "SupportsPagination": true,
            "PaginationType": "PageNumber",
            "SupportsIncrementalSync": true,
            "SupportsWrite": true,
            "Sequence": 38,
            "Status": "Active"
          },
          "relatedEntities": {
            "MJ: Integration Object Fields": [
              {
                "fields": {
                  "IntegrationObjectID": "@parent:ID",
                  "Name": "memberId",
                  "DisplayName": "memberId",
                  "Type": "nvarchar",
                  "Length": 255,
                  "IsPrimaryKey": true,
                  "IsForeignKey": true,
                  "IsRequired": true,
                  "IsReadOnly": true,
                  "IsUniqueKey": true,
                  "AllowsNull": false,
                  "Sequence": 1,
                  "Status": "Active"
                }
              }
            ]
          }
        },
        {
          "fields": {
            "IntegrationID": "@parent:ID",
            "Name": "CustomerInfos",
            "DisplayName": "Customer Info",
            "Description": "Customer master info records",
            "Category": "Core",
            "APIPath": "/CustomerInfos",
            "ResponseDataKey": "data",
            "DefaultPageSize": 200,
            "SupportsPagination": true,
            "PaginationType": "PageNumber",
            "SupportsIncrementalSync": true,
            "SupportsWrite": true,
            "Sequence": 39,
            "Status": "Active"
          },
          "relatedEntities": {
            "MJ: Integration Object Fields": [
              {
                "fields": {
                  "IntegrationObjectID": "@parent:ID",
                  "Name": "id",
                  "DisplayName": "id",
                  "Type": "nvarchar",
                  "Length": 255,
                  "IsPrimaryKey": true,
                  "IsForeignKey": false,
                  "IsRequired": true,
                  "IsReadOnly": true,
                  "IsUniqueKey": true,
                  "AllowsNull": false,
                  "Sequence": 1,
                  "Status": "Active"
                }
              },
              {
                "fields": {
                  "IntegrationObjectID": "@parent:ID",
                  "Name": "modifiedOn",
                  "DisplayName": "modifiedOn",
                  "Type": "datetime",
                  "Length": null,
                  "IsPrimaryKey": false,
                  "IsForeignKey": false,
                  "IsRequired": false,
                  "IsReadOnly": true,
                  "IsUniqueKey": false,
                  "AllowsNull": true,
                  "Sequence": 2,
                  "Status": "Active"
                }
              }
            ]
          }
        },
        {
          "fields": {
            "IntegrationID": "@parent:ID",
            "Name": "Countries",
            "DisplayName": "Country",
            "Description": "Country code lookup",
            "Category": "Core",
            "APIPath": "/Countries",
            "ResponseDataKey": "data",
            "DefaultPageSize": 200,
            "SupportsPagination": true,
            "PaginationType": "PageNumber",
            "SupportsIncrementalSync": true,
            "SupportsWrite": false,
            "Sequence": 40,
            "Status": "Active"
          },
          "relatedEntities": {
            "MJ: Integration Object Fields": [
              {
                "fields": {
                  "IntegrationObjectID": "@parent:ID",
                  "Name": "id",
                  "DisplayName": "id",
                  "Type": "nvarchar",
                  "Length": 255,
                  "IsPrimaryKey": true,
                  "IsForeignKey": false,
                  "IsRequired": true,
                  "IsReadOnly": true,
                  "IsUniqueKey": true,
                  "AllowsNull": false,
                  "Sequence": 1,
                  "Status": "Active"
                }
              }
            ]
          }
        },
        {
          "fields": {
            "IntegrationID": "@parent:ID",
            "Name": "States",
            "DisplayName": "State",
            "Description": "State/province code lookup",
            "Category": "Core",
            "APIPath": "/States",
            "ResponseDataKey": "data",
            "DefaultPageSize": 200,
            "SupportsPagination": true,
            "PaginationType": "PageNumber",
            "SupportsIncrementalSync": true,
            "SupportsWrite": false,
            "Sequence": 41,
            "Status": "Active"
          },
          "relatedEntities": {
            "MJ: Integration Object Fields": [
              {
                "fields": {
                  "IntegrationObjectID": "@parent:ID",
                  "Name": "id",
                  "DisplayName": "id",
                  "Type": "nvarchar",
                  "Length": 255,
                  "IsPrimaryKey": true,
                  "IsForeignKey": false,
                  "IsRequired": true,
                  "IsReadOnly": true,
                  "IsUniqueKey": true,
                  "AllowsNull": false,
                  "Sequence": 1,
                  "Status": "Active"
                }
              }
            ]
          }
        },
        {
          "fields": {
            "IntegrationID": "@parent:ID",
            "Name": "CodeTables",
            "DisplayName": "Code Table",
            "Description": "Generic code table values",
            "Category": "Core",
            "APIPath": "/CodeTables",
            "ResponseDataKey": "data",
            "DefaultPageSize": 200,
            "SupportsPagination": true,
            "PaginationType": "PageNumber",
            "SupportsIncrementalSync": true,
            "SupportsWrite": false,
            "Sequence": 42,
            "Status": "Active"
          },
          "relatedEntities": {
            "MJ: Integration Object Fields": [
              {
                "fields": {
                  "IntegrationObjectID": "@parent:ID",
                  "Name": "id",
                  "DisplayName": "id",
                  "Type": "nvarchar",
                  "Length": 255,
                  "IsPrimaryKey": true,
                  "IsForeignKey": false,
                  "IsRequired": true,
                  "IsReadOnly": true,
                  "IsUniqueKey": true,
                  "AllowsNull": false,
                  "Sequence": 1,
                  "Status": "Active"
                }
              }
            ]
          }
        },
        {
          "fields": {
            "IntegrationID": "@parent:ID",
            "Name": "P360CustomFields",
            "DisplayName": "Custom Field Def",
            "Description": "Custom field definitions",
            "Category": "Core",
            "APIPath": "/P360CustomFields",
            "ResponseDataKey": "data",
            "DefaultPageSize": 200,
            "SupportsPagination": true,
            "PaginationType": "PageNumber",
            "SupportsIncrementalSync": true,
            "SupportsWrite": false,
            "Sequence": 43,
            "Status": "Active"
          },
          "relatedEntities": {
            "MJ: Integration Object Fields": [
              {
                "fields": {
                  "IntegrationObjectID": "@parent:ID",
                  "Name": "id",
                  "DisplayName": "id",
                  "Type": "nvarchar",
                  "Length": 255,
                  "IsPrimaryKey": true,
                  "IsForeignKey": false,
                  "IsRequired": true,
                  "IsReadOnly": true,
                  "IsUniqueKey": true,
                  "AllowsNull": false,
                  "Sequence": 1,
                  "Status": "Active"
                }
              }
            ]
          }
        }
      ]
    }
  }
]
